fibonacci/Fibonacci.py
fibonacci/__init__.py
fibonacci_btu-0.0.7.dist-info/LICENSE
fibonacci_btu-0.0.7.dist-info/METADATA
fibonacci_btu-0.0.7.dist-info/WHEEL
fibonacci_btu-0.0.7.dist-info/top_level.txt
fibonacci_btu-0.0.7.dist-info/RECORD
