Metadata-Version: 2.1
Name: fibonacci-btu
Version: 0.0.7
Summary: Module that lets you access specific index of Fibonnacis sequence
Home-page: https://github.com/pypa/sampleproject
Author: Mirian Tsirekidze
Author-email: mirian.tsirekidze.1@btu.edu.ge
Project-URL: Bug Tracker, https://github.com/pypa/sampleproject/issues
Classifier: Programming Language :: Python :: 3
Classifier: License :: OSI Approved :: MIT License
Classifier: Operating System :: OS Independent
Requires-Python: >=3.6
License-File: LICENSE
